{
   "Alignment" : null,
   "Point" : null,
   "actors" : [
      {
         "Alignment" : [ 0, 0 ],
         "Alpha" : 1.0,
         "Angle" : 0.0,
         "Colour" : 4294967295,
         "Flip" : 0,
         "Position" : [ 0.0, -1.0 ],
         "Scale" : [ 1.0, 1.0 ],
         "Shown" : true,
         "sprite" : "dartling_gun_skin_icon",
         "type" : 1,
         "uid" : 15
      },
      {
         "Alignment" : [ 0, 0 ],
         "Alpha" : 1.0,
         "Angle" : 0.0,
         "Colour" : 4294967295,
         "Flip" : 0,
         "Position" : [ -38.0, 5.0 ],
         "Scale" : [ 1.0, 1.0 ],
         "Shown" : false,
         "sprite" : "bomb_tower_explosion_01",
         "type" : 1,
         "uid" : 16
      },
      {
         "Alignment" : [ 0, 0 ],
         "Alpha" : 1.0,
         "Angle" : 0.0,
         "Colour" : 4294967295,
         "Flip" : 0,
         "Position" : [ -38.0, 5.0 ],
         "Scale" : [ 1.0, 1.0 ],
         "Shown" : false,
         "sprite" : "bomb_tower_explosion_02",
         "type" : 1,
         "uid" : 17
      },
      {
         "Alignment" : [ 0, 0 ],
         "Alpha" : 1.0,
         "Angle" : 0.0,
         "Colour" : 4294967295,
         "Flip" : 0,
         "Position" : [ -38.0, 5.0 ],
         "Scale" : [ 0.750, 0.750 ],
         "Shown" : false,
         "sprite" : "bomb_tower_explosion_03",
         "type" : 1,
         "uid" : 18
      },
      {
         "Alignment" : [ 0, 0 ],
         "Alpha" : 1.0,
         "Angle" : 0.0,
         "Colour" : 4294967295,
         "Flip" : 0,
         "Position" : [ -38.0, 5.0 ],
         "Scale" : [ 1.0, 1.0 ],
         "Shown" : false,
         "sprite" : "bomb_tower_explosion_04",
         "type" : 1,
         "uid" : 19
      }
   ],
   "customvariables" : null,
   "labels" : null,
   "stageOptions" : {
      "SpriteInfo" : [
         {
            "SpriteInfo" : "dartling_gun_skin_icon",
            "Texture" : "shop_currency"
         },
         {
            "SpriteInfo" : "bomb_tower_explosion_01",
            "Texture" : "shop_currency"
         },
         {
            "SpriteInfo" : "bomb_tower_explosion_02",
            "Texture" : "shop_currency"
         },
         {
            "SpriteInfo" : "bomb_tower_explosion_03",
            "Texture" : "shop_currency"
         },
         {
            "SpriteInfo" : "bomb_tower_explosion_04",
            "Texture" : "shop_currency"
         }
      ],
      "StageLength" : 1.493923664093018,
      "Version" : 1
   },
   "timelines" : [
      {
         "spriteuid" : 19,
         "stage" : [
            {
               "Alignment" : [ 0, 0 ],
               "Alpha" : 1.0,
               "Angle" : 0.0,
               "Colour" : 4294967295,
               "Flip" : 0,
               "Position" : [ -38.0, 5.0 ],
               "Scale" : [ 1.0, 1.0 ],
               "Shown" : false,
               "Time" : 0.0
            },
            {
               "Alignment" : [ 0, 0 ],
               "Alpha" : 1.0,
               "Angle" : 0.0,
               "Colour" : 4294967295,
               "Flip" : 0,
               "Position" : [ -38.0, 5.0 ],
               "Scale" : [ 1.0, 1.0 ],
               "Shown" : true,
               "Time" : 0.2465277761220932
            },
            {
               "Alignment" : [ 0, 0 ],
               "Alpha" : 1.0,
               "Angle" : 0.0,
               "Colour" : 4294967295,
               "Flip" : 0,
               "Position" : [ -38.0, 5.0 ],
               "Scale" : [ 1.0, 1.0 ],
               "Shown" : false,
               "Time" : 0.2968750
            },
            {
               "Alignment" : [ 0, 0 ],
               "Alpha" : 1.0,
               "Angle" : 0.0,
               "Colour" : 4294967295,
               "Flip" : 0,
               "Position" : [ -38.0, 5.0 ],
               "Scale" : [ 1.0, 1.0 ],
               "Shown" : true,
               "Time" : 0.4513888955116272
            },
            {
               "Alignment" : [ 0, 0 ],
               "Alpha" : 1.0,
               "Angle" : 0.0,
               "Colour" : 4294967295,
               "Flip" : 0,
               "Position" : [ -38.0, 5.0 ],
               "Scale" : [ 1.0, 1.0 ],
               "Shown" : false,
               "Time" : 0.5017361044883728
            },
            {
               "Alignment" : [ 0, 0 ],
               "Alpha" : 1.0,
               "Angle" : 0.0,
               "Colour" : 4294967295,
               "Flip" : 0,
               "Position" : [ -38.0, 5.0 ],
               "Scale" : [ 1.0, 1.0 ],
               "Shown" : true,
               "Time" : 0.6510416269302368
            },
            {
               "Alignment" : [ 0, 0 ],
               "Alpha" : 1.0,
               "Angle" : 0.0,
               "Colour" : 4294967295,
               "Flip" : 0,
               "Position" : [ -38.0, 5.0 ],
               "Scale" : [ 1.0, 1.0 ],
               "Shown" : false,
               "Time" : 0.7031250
            }
         ]
      },
      {
         "spriteuid" : 17,
         "stage" : [
            {
               "Alignment" : [ 0, 0 ],
               "Alpha" : 1.0,
               "Angle" : 0.0,
               "Colour" : 4294967295,
               "Flip" : 0,
               "Position" : [ -38.0, 5.0 ],
               "Scale" : [ 1.0, 1.0 ],
               "Shown" : false,
               "Time" : 0.0
            },
            {
               "Alignment" : [ 0, 0 ],
               "Alpha" : 1.0,
               "Angle" : 0.0,
               "Colour" : 4294967295,
               "Flip" : 0,
               "Position" : [ -38.0, 5.0 ],
               "Scale" : [ 1.0, 1.0 ],
               "Shown" : true,
               "Time" : 0.1510416567325592
            },
            {
               "Alignment" : [ 0, 0 ],
               "Alpha" : 1.0,
               "Angle" : 0.0,
               "Colour" : 4294967295,
               "Flip" : 0,
               "Position" : [ -38.0, 5.0 ],
               "Scale" : [ 1.0, 1.0 ],
               "Shown" : false,
               "Time" : 0.1996527761220932
            },
            {
               "Alignment" : [ 0, 0 ],
               "Alpha" : 1.0,
               "Angle" : 0.0,
               "Colour" : 4294967295,
               "Flip" : 0,
               "Position" : [ -38.0, 5.0 ],
               "Scale" : [ 1.0, 1.0 ],
               "Shown" : true,
               "Time" : 0.3489583432674408
            },
            {
               "Alignment" : [ 0, 0 ],
               "Alpha" : 1.0,
               "Angle" : 0.0,
               "Colour" : 4294967295,
               "Flip" : 0,
               "Position" : [ -38.0, 5.0 ],
               "Scale" : [ 1.0, 1.0 ],
               "Shown" : false,
               "Time" : 0.4010416567325592
            },
            {
               "Alignment" : [ 0, 0 ],
               "Alpha" : 1.0,
               "Angle" : 0.0,
               "Colour" : 4294967295,
               "Flip" : 0,
               "Position" : [ -38.0, 5.0 ],
               "Scale" : [ 1.0, 1.0 ],
               "Shown" : true,
               "Time" : 0.5468750
            },
            {
               "Alignment" : [ 0, 0 ],
               "Alpha" : 1.0,
               "Angle" : 0.0,
               "Colour" : 4294967295,
               "Flip" : 0,
               "Position" : [ -38.0, 5.0 ],
               "Scale" : [ 1.0, 1.0 ],
               "Shown" : false,
               "Time" : 0.5989583134651184
            }
         ]
      },
      {
         "spriteuid" : 18,
         "stage" : [
            {
               "Alignment" : [ 0, 0 ],
               "Alpha" : 1.0,
               "Angle" : 0.0,
               "Colour" : 4294967295,
               "Flip" : 0,
               "Position" : [ -38.0, 5.0 ],
               "Scale" : [ 0.750, 0.750 ],
               "Shown" : false,
               "Time" : 0.0
            },
            {
               "Alignment" : [ 0, 0 ],
               "Alpha" : 1.0,
               "Angle" : 0.0,
               "Colour" : 4294967295,
               "Flip" : 0,
               "Position" : [ -38.0, 5.0 ],
               "Scale" : [ 0.750, 0.750 ],
               "Shown" : true,
               "Time" : 0.1996527761220932
            },
            {
               "Alignment" : [ 0, 0 ],
               "Alpha" : 1.0,
               "Angle" : 0.0,
               "Colour" : 4294967295,
               "Flip" : 0,
               "Position" : [ -38.0, 5.0 ],
               "Scale" : [ 0.750, 0.750 ],
               "Shown" : false,
               "Time" : 0.2465277761220932
            },
            {
               "Alignment" : [ 0, 0 ],
               "Alpha" : 1.0,
               "Angle" : 0.0,
               "Colour" : 4294967295,
               "Flip" : 0,
               "Position" : [ -38.0, 5.0 ],
               "Scale" : [ 0.750, 0.750 ],
               "Shown" : true,
               "Time" : 0.4010416567325592
            },
            {
               "Alignment" : [ 0, 0 ],
               "Alpha" : 1.0,
               "Angle" : 0.0,
               "Colour" : 4294967295,
               "Flip" : 0,
               "Position" : [ -38.0, 5.0 ],
               "Scale" : [ 0.750, 0.750 ],
               "Shown" : false,
               "Time" : 0.4513888955116272
            },
            {
               "Alignment" : [ 0, 0 ],
               "Alpha" : 1.0,
               "Angle" : 0.0,
               "Colour" : 4294967295,
               "Flip" : 0,
               "Position" : [ -38.0, 5.0 ],
               "Scale" : [ 0.750, 0.750 ],
               "Shown" : true,
               "Time" : 0.5989583134651184
            },
            {
               "Alignment" : [ 0, 0 ],
               "Alpha" : 1.0,
               "Angle" : 0.0,
               "Colour" : 4294967295,
               "Flip" : 0,
               "Position" : [ -38.0, 5.0 ],
               "Scale" : [ 0.750, 0.750 ],
               "Shown" : false,
               "Time" : 0.6510416269302368
            }
         ]
      },
      {
         "spriteuid" : 16,
         "stage" : [
            {
               "Alignment" : [ 0, 0 ],
               "Alpha" : 1.0,
               "Angle" : 0.0,
               "Colour" : 4294967295,
               "Flip" : 0,
               "Position" : [ -38.0, 5.0 ],
               "Scale" : [ 1.0, 1.0 ],
               "Shown" : false,
               "Time" : 0.0
            },
            {
               "Alignment" : [ 0, 0 ],
               "Alpha" : 1.0,
               "Angle" : 0.0,
               "Colour" : 4294967295,
               "Flip" : 0,
               "Position" : [ -38.0, 5.0 ],
               "Scale" : [ 1.0, 1.0 ],
               "Shown" : true,
               "Time" : 0.1024305522441864
            },
            {
               "Alignment" : [ 0, 0 ],
               "Alpha" : 1.0,
               "Angle" : 0.0,
               "Colour" : 4294967295,
               "Flip" : 0,
               "Position" : [ -38.0, 5.0 ],
               "Scale" : [ 1.0, 1.0 ],
               "Shown" : false,
               "Time" : 0.1510416567325592
            },
            {
               "Alignment" : [ 0, 0 ],
               "Alpha" : 1.0,
               "Angle" : 0.0,
               "Colour" : 4294967295,
               "Flip" : 0,
               "Position" : [ -38.0, 5.0 ],
               "Scale" : [ 1.0, 1.0 ],
               "Shown" : true,
               "Time" : 0.2968750
            },
            {
               "Alignment" : [ 0, 0 ],
               "Alpha" : 1.0,
               "Angle" : 0.0,
               "Colour" : 4294967295,
               "Flip" : 0,
               "Position" : [ -38.0, 5.0 ],
               "Scale" : [ 1.0, 1.0 ],
               "Shown" : false,
               "Time" : 0.3489583432674408
            },
            {
               "Alignment" : [ 0, 0 ],
               "Alpha" : 1.0,
               "Angle" : 0.0,
               "Colour" : 4294967295,
               "Flip" : 0,
               "Position" : [ -38.0, 5.0 ],
               "Scale" : [ 1.0, 1.0 ],
               "Shown" : true,
               "Time" : 0.5034722089767456
            },
            {
               "Alignment" : [ 0, 0 ],
               "Alpha" : 1.0,
               "Angle" : 0.0,
               "Colour" : 4294967295,
               "Flip" : 0,
               "Position" : [ -38.0, 5.0 ],
               "Scale" : [ 1.0, 1.0 ],
               "Shown" : false,
               "Time" : 0.5468750
            }
         ]
      },
      {
         "spriteuid" : 15,
         "stage" : null
      }
   ]
}
