{
   "Alignment" : null,
   "Point" : null,
   "actors" : [
      {
         "Alignment" : [ 0, 0 ],
         "Alpha" : 0.5176470875740051,
         "Angle" : 0.0,
         "Colour" : 2231369727,
         "Flip" : 0,
         "Position" : [ 0.0, 0.0 ],
         "Scale" : [ 0.4499999880790710, 0.4499999880790710 ],
         "Shown" : true,
         "sprite" : "bloonarius_ripple",
         "type" : 1,
         "uid" : 1
      }
   ],
   "customvariables" : null,
   "labels" : null,
   "stageOptions" : {
      "SpriteInfo" : [
         {
            "SpriteInfo" : "bloonarius_ripple",
            "Texture" : "bloonarius"
         }
      ],
      "StageLength" : 1.980902791023254,
      "Version" : 1
   },
   "timelines" : [
      {
         "spriteuid" : 1,
         "stage" : [
            {
               "Alignment" : [ 0, 0 ],
               "Alpha" : 0.5176470875740051,
               "Angle" : 0.0,
               "Colour" : 2231369727,
               "Flip" : 0,
               "Position" : [ 0.0, 0.0 ],
               "Scale" : [ 0.4499999880790710, 0.4499999880790710 ],
               "Shown" : true,
               "Time" : 0.0
            },
            {
               "Alignment" : [ 0, 0 ],
               "Alpha" : 0.0,
               "Angle" : 0.0,
               "Colour" : 16777215,
               "Flip" : 0,
               "Position" : [ 0.0, 0.0 ],
               "Scale" : [ 0.2000000029802322, 0.2000000029802322 ],
               "Shown" : true,
               "Time" : 0.0
            },
            {
               "Alignment" : [ 0, 0 ],
               "Alpha" : 0.5176470875740051,
               "Angle" : 0.0,
               "Colour" : 2231369727,
               "Flip" : 0,
               "Position" : [ 0.0, 0.0 ],
               "Scale" : [ 0.4499999880790710, 0.4499999880790710 ],
               "Shown" : true,
               "Time" : 2.0
            },
            {
               "Alignment" : [ 0, 0 ],
               "Alpha" : 0.9686274528503418,
               "Angle" : 0.0,
               "Colour" : 4160749567,
               "Flip" : 0,
               "Position" : [ 0.0, 0.0 ],
               "Scale" : [ 0.9193103313446045, 0.9193103313446045 ],
               "Shown" : true,
               "Time" : 0.5069444179534912
            },
            {
               "Alignment" : [ 0, 0 ],
               "Alpha" : 0.0,
               "Angle" : 0.0,
               "Colour" : 16777215,
               "Flip" : 0,
               "Position" : [ 0.0, 0.0 ],
               "Scale" : [ 1.597652912139893, 1.597652912139893 ],
               "Shown" : false,
               "Time" : 1.513888835906982
            },
            {
               "Alignment" : [ 0, 0 ],
               "Alpha" : 0.0,
               "Angle" : 0.0,
               "Colour" : 16777215,
               "Flip" : 0,
               "Position" : [ 0.0, 0.0 ],
               "Scale" : [ 0.250, 0.250 ],
               "Shown" : true,
               "Time" : 1.520833373069763
            }
         ]
      }
   ]
}
