{
   "actors" : [
      {
         "Alignment" : [ 0, 0 ],
         "Alpha" : 1.0,
         "Angle" : 0.0,
         "Colour" : 4294967295,
         "Flip" : 0,
         "Position" : [ 0.0, 0.0 ],
         "Scale" : [ 1.0, 1.0 ],
         "Shown" : true,
         "sprite" : "FrostedCornerscompoundsprite.json",
         "type" : 2,
         "uid" : 3
      },
      {
         "Alignment" : [ 0, 0 ],
         "Alpha" : 1.0,
         "Angle" : 0.0,
         "Colour" : 4294967295,
         "Flip" : 0,
         "Position" : [ -4.0, -6.0 ],
         "Scale" : [ 1.0, 1.0 ],
         "Shown" : true,
         "sprite" : "SnowStormcompoundsprite.json",
         "type" : 2,
         "uid" : 1
      },
      {
         "Alignment" : [ 0, 0 ],
         "Alpha" : 1.0,
         "Angle" : 0.0,
         "Colour" : 4294967295,
         "Flip" : 2,
         "Position" : [ -4.0, 5.0 ],
         "Scale" : [ 1.0, 1.0 ],
         "Shown" : true,
         "sprite" : "SnowStormcompoundsprite.json",
         "type" : 2,
         "uid" : 2
      },
      {
         "Alignment" : [ 0, 0 ],
         "Alpha" : 1.0,
         "Angle" : 0.0,
         "Colour" : 4294967295,
         "Flip" : 0,
         "Position" : [ 1.0, -3.0 ],
         "Scale" : [ 1.0, 1.0 ],
         "Shown" : true,
         "sprite" : "SnowStorm2compoundsprite.json",
         "type" : 2,
         "uid" : 4
      },
      {
         "Alignment" : [ 0, 0 ],
         "Alpha" : 1.0,
         "Angle" : 0.0,
         "Colour" : 4294967295,
         "Flip" : 0,
         "Position" : [ 460.0, -207.0 ],
         "Scale" : [ 10.0, 10.0 ],
         "Shown" : true,
         "sprite" : "absolute_zero_wind_01",
         "type" : 1,
         "uid" : 5
      },
      {
         "Alignment" : [ 0, 0 ],
         "Alpha" : 1.0,
         "Angle" : 0.0,
         "Colour" : 4294967295,
         "Flip" : 0,
         "Position" : [ 563.0, 0.0 ],
         "Scale" : [ 10.0, 10.0 ],
         "Shown" : true,
         "sprite" : "absolute_zero_wind_01",
         "type" : 1,
         "uid" : 6
      },
      {
         "Alignment" : [ 0, 0 ],
         "Alpha" : 1.0,
         "Angle" : 0.0,
         "Colour" : 4294967295,
         "Flip" : 0,
         "Position" : [ 773.0, 189.0 ],
         "Scale" : [ 10.0, 10.0 ],
         "Shown" : true,
         "sprite" : "absolute_zero_wind_01",
         "type" : 1,
         "uid" : 7
      }
   ],
   "customvariables" : null,
   "events" : null,
   "labels" : null,
   "stageOptions" : {
      "SpriteInfo" : [
         {
            "SpriteInfo" : "FrostedCornerscompoundsprite.json",
            "Texture" : "InGame"
         },
         {
            "SpriteInfo" : "SnowStormcompoundsprite.json",
            "Texture" : "InGame"
         },
         {
            "SpriteInfo" : "SnowStorm2compoundsprite.json",
            "Texture" : "InGame"
         },
         {
            "SpriteInfo" : "absolute_zero_wind_01",
            "Texture" : "InGame"
         }
      ],
      "StageLength" : 4.0,
      "Version" : 1
   },
   "timelines" : [
      {
         "spriteuid" : 3,
         "stage" : [
            {
               "Alignment" : [ 0, 0 ],
               "Alpha" : 1.0,
               "Angle" : 0.0,
               "Colour" : 4294967295,
               "Flip" : 0,
               "Position" : [ 0.0, 0.0 ],
               "Scale" : [ 1.0, 1.0 ],
               "Shown" : true,
               "Time" : 0.0
            },
            {
               "Alignment" : [ 0, 0 ],
               "Alpha" : 1.0,
               "Angle" : 0.0,
               "Colour" : 4294967295,
               "Flip" : 0,
               "Position" : [ 0.0, 0.0 ],
               "Scale" : [ 1.0, 1.0 ],
               "Shown" : true,
               "Time" : 0.0
            },
            {
               "Alignment" : [ 0, 0 ],
               "Alpha" : 0.0,
               "Angle" : 0.0,
               "Colour" : 16777215,
               "Flip" : 0,
               "Position" : [ 0.0, 0.0 ],
               "Scale" : [ 1.0, 1.0 ],
               "Shown" : true,
               "Time" : 4.0
            }
         ]
      },
      {
         "spriteuid" : 2,
         "stage" : [
            {
               "Alignment" : [ 0, 0 ],
               "Alpha" : 1.0,
               "Angle" : 0.0,
               "Colour" : 4294967295,
               "Flip" : 2,
               "Position" : [ -4.0, 5.0 ],
               "Scale" : [ 1.0, 1.0 ],
               "Shown" : true,
               "Time" : 0.0
            },
            {
               "Alignment" : [ 0, 0 ],
               "Alpha" : 1.0,
               "Angle" : 0.0,
               "Colour" : 4294967295,
               "Flip" : 2,
               "Position" : [ -4.0, 5.0 ],
               "Scale" : [ 1.0, 1.0 ],
               "Shown" : true,
               "Time" : 0.0
            },
            {
               "Alignment" : [ 0, 0 ],
               "Alpha" : 0.0,
               "Angle" : 0.0,
               "Colour" : 16777215,
               "Flip" : 2,
               "Position" : [ -4.0, 5.0 ],
               "Scale" : [ 1.0, 1.0 ],
               "Shown" : true,
               "Time" : 4.0
            }
         ]
      },
      {
         "spriteuid" : 1,
         "stage" : [
            {
               "Alignment" : [ 0, 0 ],
               "Alpha" : 1.0,
               "Angle" : 0.0,
               "Colour" : 4294967295,
               "Flip" : 0,
               "Position" : [ -4.0, -6.0 ],
               "Scale" : [ 1.0, 1.0 ],
               "Shown" : true,
               "Time" : 0.0
            },
            {
               "Alignment" : [ 0, 0 ],
               "Alpha" : 1.0,
               "Angle" : 0.0,
               "Colour" : 4294967295,
               "Flip" : 0,
               "Position" : [ -4.0, -6.0 ],
               "Scale" : [ 1.0, 1.0 ],
               "Shown" : true,
               "Time" : 0.0
            },
            {
               "Alignment" : [ 0, 0 ],
               "Alpha" : 0.0,
               "Angle" : 0.0,
               "Colour" : 16777215,
               "Flip" : 0,
               "Position" : [ -4.0, -6.0 ],
               "Scale" : [ 1.0, 1.0 ],
               "Shown" : true,
               "Time" : 4.0
            }
         ]
      },
      {
         "spriteuid" : 4,
         "stage" : [
            {
               "Alignment" : [ 0, 0 ],
               "Alpha" : 1.0,
               "Angle" : 0.0,
               "Colour" : 4294967295,
               "Flip" : 0,
               "Position" : [ 1.0, -3.0 ],
               "Scale" : [ 1.0, 1.0 ],
               "Shown" : true,
               "Time" : 0.0
            },
            {
               "Alignment" : [ 0, 0 ],
               "Alpha" : 1.0,
               "Angle" : 0.0,
               "Colour" : 4294967295,
               "Flip" : 0,
               "Position" : [ 1.0, -3.0 ],
               "Scale" : [ 1.0, 1.0 ],
               "Shown" : true,
               "Time" : 0.0
            },
            {
               "Alignment" : [ 0, 0 ],
               "Alpha" : 0.0,
               "Angle" : 0.0,
               "Colour" : 16777215,
               "Flip" : 0,
               "Position" : [ 1.0, -3.0 ],
               "Scale" : [ 1.0, 1.0 ],
               "Shown" : true,
               "Time" : 4.0
            }
         ]
      },
      {
         "spriteuid" : 5,
         "stage" : [
            {
               "Alignment" : [ 0, 0 ],
               "Alpha" : 1.0,
               "Angle" : 0.0,
               "Colour" : 4294967295,
               "Flip" : 0,
               "Position" : [ 460.0, -207.0 ],
               "Scale" : [ 10.0, 10.0 ],
               "Shown" : true,
               "Time" : 0.0
            },
            {
               "Alignment" : [ 0, 0 ],
               "Alpha" : 0.478431373834610,
               "Angle" : 0.0,
               "Colour" : 2063597567,
               "Flip" : 0,
               "Position" : [ -552.0, -207.0 ],
               "Scale" : [ 10.0, 10.0 ],
               "Shown" : true,
               "Time" : 2.0
            }
         ]
      },
      {
         "spriteuid" : 6,
         "stage" : [
            {
               "Alignment" : [ 0, 0 ],
               "Alpha" : 1.0,
               "Angle" : 0.0,
               "Colour" : 4294967295,
               "Flip" : 0,
               "Position" : [ 563.0, 0.0 ],
               "Scale" : [ 10.0, 10.0 ],
               "Shown" : true,
               "Time" : 0.0
            },
            {
               "Alignment" : [ 0, 0 ],
               "Alpha" : 0.4862745106220245,
               "Angle" : 0.0,
               "Colour" : 2097151999,
               "Flip" : 0,
               "Position" : [ -595.0, 0.0 ],
               "Scale" : [ 10.0, 10.0 ],
               "Shown" : true,
               "Time" : 2.0
            }
         ]
      },
      {
         "spriteuid" : 7,
         "stage" : [
            {
               "Alignment" : [ 0, 0 ],
               "Alpha" : 1.0,
               "Angle" : 0.0,
               "Colour" : 4294967295,
               "Flip" : 0,
               "Position" : [ 773.0, 189.0 ],
               "Scale" : [ 10.0, 10.0 ],
               "Shown" : true,
               "Time" : 0.0
            },
            {
               "Alignment" : [ 0, 0 ],
               "Alpha" : 0.4862745106220245,
               "Angle" : 0.0,
               "Colour" : 2097151999,
               "Flip" : 0,
               "Position" : [ -511.0, 189.0 ],
               "Scale" : [ 10.0, 10.0 ],
               "Shown" : true,
               "Time" : 2.0
            }
         ]
      }
   ]
}
