{
   "Alignment" : null,
   "Point" : null,
   "actors" : [
      {
         "Alignment" : [ 0, 0 ],
         "Alpha" : 1.0,
         "Angle" : 0.0,
         "Colour" : 4294967295,
         "Flip" : 0,
         "Position" : [ 0.0, 0.0 ],
         "Scale" : [ 1.0, 1.0 ],
         "Shown" : true,
         "sprite" : "limited_time_only",
         "type" : 1,
         "uid" : 1
      }
   ],
   "customvariables" : null,
   "events" : null,
   "labels" : null,
   "stageOptions" : {
      "SpriteInfo" : [
         {
            "SpriteInfo" : "limited_time_only",
            "Texture" : "lobby_screen"
         }
      ],
      "StageLength" : 3.0,
      "Version" : 1
   },
   "timelines" : [
      {
         "spriteuid" : 1,
         "stage" : [
            {
               "Alignment" : [ 0, 0 ],
               "Alpha" : 1.0,
               "Angle" : 0.0,
               "Colour" : 4294967295,
               "Flip" : 0,
               "Position" : [ 0.0, 0.0 ],
               "Scale" : [ 1.0, 1.0 ],
               "Shown" : true,
               "Time" : 0.0
            },
            {
               "Alignment" : [ 0, 0 ],
               "Alpha" : 1.0,
               "Angle" : -30.0,
               "Colour" : 4294967295,
               "Flip" : 0,
               "Position" : [ 0.0, 0.0 ],
               "Scale" : [ 1.0, 1.0 ],
               "Shown" : true,
               "Time" : 0.0
            },
            {
               "Alignment" : [ 0, 0 ],
               "Alpha" : 1.0,
               "Angle" : 0.0,
               "Colour" : 4294967295,
               "Flip" : 0,
               "Position" : [ 0.0, 0.0 ],
               "Scale" : [ 1.0, 1.0 ],
               "Shown" : true,
               "Time" : 0.4761904776096344
            },
            {
               "Alignment" : [ 0, 0 ],
               "Alpha" : 1.0,
               "Angle" : 0.0,
               "Colour" : 4294967295,
               "Flip" : 0,
               "Position" : [ 0.0, 0.0 ],
               "Scale" : [ 0.8000000119209290, 0.8000000119209290 ],
               "Shown" : true,
               "Time" : 0.6938775777816773
            },
            {
               "Alignment" : [ 0, 0 ],
               "Alpha" : 1.0,
               "Angle" : 0.0,
               "Colour" : 4294967295,
               "Flip" : 0,
               "Position" : [ 0.0, 0.0 ],
               "Scale" : [ 1.100000023841858, 1.100000023841858 ],
               "Shown" : true,
               "Time" : 0.9115646481513977
            },
            {
               "Alignment" : [ 0, 0 ],
               "Alpha" : 1.0,
               "Angle" : 0.0,
               "Colour" : 4294967295,
               "Flip" : 0,
               "Position" : [ 0.0, 0.0 ],
               "Scale" : [ 0.9499999880790710, 0.9499999880790710 ],
               "Shown" : true,
               "Time" : 1.183673501014710
            },
            {
               "Alignment" : [ 0, 0 ],
               "Alpha" : 1.0,
               "Angle" : 0.0,
               "Colour" : 4294967295,
               "Flip" : 0,
               "Position" : [ 0.0, 0.0 ],
               "Scale" : [ 1.0, 1.0 ],
               "Shown" : true,
               "Time" : 1.265306115150452
            }
         ]
      }
   ]
}
