{
   "Alignment" : null,
   "Point" : null,
   "actors" : [
      {
         "Alignment" : [ 0, 0 ],
         "Alpha" : 1.0,
         "Angle" : 0.0,
         "Colour" : 4294967295,
         "Flip" : 0,
         "Position" : [ 0.0, 0.0 ],
         "Scale" : [ 0.0, 0.0 ],
         "Shown" : true,
         "sprite" : "_weekly_roundup_red.json",
         "type" : 2,
         "uid" : 1
      }
   ],
   "customvariables" : null,
   "labels" : null,
   "stageOptions" : {
      "SpriteInfo" : [
         {
            "SpriteInfo" : "_weekly_roundup_red.json",
            "Texture" : "lobby_screen"
         }
      ],
      "StageLength" : 0.3376736044883728,
      "Version" : 1
   },
   "timelines" : [
      {
         "spriteuid" : 1,
         "stage" : [
            {
               "Alignment" : [ 0, 0 ],
               "Alpha" : 1.0,
               "Angle" : 0.0,
               "Colour" : 4294967295,
               "Flip" : 0,
               "Position" : [ 0.0, 0.0 ],
               "Scale" : [ 0.0, 0.0 ],
               "Shown" : true,
               "Time" : 0.0
            },
            {
               "Alignment" : [ 0, 0 ],
               "Alpha" : 1.0,
               "Angle" : 0.0,
               "Colour" : 4294967295,
               "Flip" : 0,
               "Position" : [ 0.0, 0.0 ],
               "Scale" : [ 1.250, 1.250 ],
               "Shown" : true,
               "Time" : 0.09722222387790680
            },
            {
               "Alignment" : [ 0, 0 ],
               "Alpha" : 1.0,
               "Angle" : 0.0,
               "Colour" : 4294967295,
               "Flip" : 0,
               "Position" : [ 0.0, 0.0 ],
               "Scale" : [ 0.8999999761581421, 0.8999999761581421 ],
               "Shown" : true,
               "Time" : 0.1996527761220932
            },
            {
               "Alignment" : [ 0, 0 ],
               "Alpha" : 1.0,
               "Angle" : 0.0,
               "Colour" : 4294967295,
               "Flip" : 0,
               "Position" : [ 0.0, 0.0 ],
               "Scale" : [ 1.049999952316284, 1.049999952316284 ],
               "Shown" : true,
               "Time" : 0.2725694477558136
            },
            {
               "Alignment" : [ 0, 0 ],
               "Alpha" : 1.0,
               "Angle" : 0.0,
               "Colour" : 4294967295,
               "Flip" : 0,
               "Position" : [ 0.0, 0.0 ],
               "Scale" : [ 1.0, 1.0 ],
               "Shown" : true,
               "Time" : 0.3263888955116272
            }
         ]
      }
   ]
}
