{
   "Alignment" : null,
   "Point" : null,
   "actors" : [
      {
         "Alignment" : [ 0, 0 ],
         "Alpha" : 1.0,
         "Angle" : 0.0,
         "Colour" : 4294967295,
         "Flip" : 0,
         "Position" : [ 0.0, 0.0 ],
         "Scale" : [ 0.6000000238418579, 0.6000000238418579 ],
         "Shown" : true,
         "sprite" : "selected_tower_recess",
         "type" : 1,
         "uid" : 3
      },
      {
         "Alignment" : [ 0, 0 ],
         "Alpha" : 1.0,
         "Angle" : 0.0,
         "Colour" : 4294967295,
         "Flip" : 0,
         "Position" : [ 0.0, 0.0 ],
         "Scale" : [ 0.6000000238418579, 0.6000000238418579 ],
         "Shown" : true,
         "sprite" : "selected_tower_04_text",
         "type" : 1,
         "uid" : 4
      },
      {
         "Alignment" : [ 0, 0 ],
         "Alpha" : 1.0,
         "Angle" : 0.0,
         "Colour" : 4294967295,
         "Flip" : 0,
         "Position" : [ 0.0, 0.0 ],
         "Scale" : [ 0.6499999761581421, 0.6499999761581421 ],
         "Shown" : true,
         "sprite" : "cross.json",
         "type" : 2,
         "uid" : 1
      }
   ],
   "customvariables" : null,
   "labels" : null,
   "stageOptions" : {
      "SpriteInfo" : [
         {
            "SpriteInfo" : "selected_tower_recess",
            "Texture" : "lobby_screen"
         },
         {
            "SpriteInfo" : "selected_tower_04_text",
            "Texture" : "lobby_screen"
         },
         {
            "SpriteInfo" : "cross.json",
            "Texture" : "lobby_screen"
         }
      ],
      "StageLength" : 20.0,
      "Version" : 1
   },
   "timelines" : [
      {
         "spriteuid" : 4,
         "stage" : null
      },
      {
         "spriteuid" : 3,
         "stage" : null
      },
      {
         "spriteuid" : 1,
         "stage" : null
      }
   ]
}
