{
    "Bloon": {
        "BackgroundSprite": "moonlight", 
        "Cost": 3000, 
        "Features": [
            "Spaced"
        ], 
        "IncomeChange": -120, 
        "Interval": 5.0, 
        "NumBloons": 1, 
        "Type": "BFB", 
        "UnlockRound": 17
    }, 
    "CardSet": "Basic", 
    "CardSprite": "green", 
    "DiscardCost": 1600, 
    "Name": "18", 
    "NameOld": "MonkeyApprentice30_BFBSpaced1", 
    "StartingCard": true, 
    "Tower": {
        "BackgroundSprite": "thunderstorm", 
        "Cost": 3000, 
        "Features": [
            "PopLead", 
            "PopBlack", 
            "PopFrozen", 
            "PopWhite"
        ], 
        "Type": "MonkeyApprentice", 
        "Upgrades": [
            3, 
            0
        ]
    }, 
    "UnlockMethod": "Unlocked", 
    "Visible": true
}